litellm_types/__init__.py
litellm_types/completion.py
litellm_types/document.py
litellm_types/messages.py
litellm_types/prompt.py
litellm_types/test.py
litellm_types-0.0.16.dist-info/LICENSE
litellm_types-0.0.16.dist-info/METADATA
litellm_types-0.0.16.dist-info/WHEEL
litellm_types-0.0.16.dist-info/top_level.txt
litellm_types-0.0.16.dist-info/RECORD
