Metadata-Version: 2.1
Name: litellm_types
Version: 0.0.16
License-File: LICENSE
Requires-Dist: pydantic
Requires-Dist: litellm
Requires-Dist: beartype
Requires-Dist: rich
Requires-Dist: tenacity
